flac/__init__.py
flac/app.py
flac/cli.py
flac/config.py
flac/database.py
flac/logging.py
flac/model.py
flac/testing.py
flac/utils.py
flac/version.py
flac/contrib/gunicorn.py
flac/contrib/sentry.py
flac/contrib/shiv.py
flac/contrib/sqlalchemy.py
flask_flac-0.20250728.1.dist-info/METADATA
flask_flac-0.20250728.1.dist-info/WHEEL
flask_flac-0.20250728.1.dist-info/RECORD
