Metadata-Version: 2.4
Name: flask-flac
Version: 0.20250728.1
Summary: Flask based library to help structure an application with an eye towards CLI apps, not just web.
Author-email: Randy Syring <randy@syrings.us>
License-Expression: MIT
Requires-Python: >=3.12
Requires-Dist: flask>=3.1.1
Requires-Dist: platformdirs>=4.3.8
Requires-Dist: python-json-logger>=3.3.0
Provides-Extra: sqlalchemy
Requires-Dist: arrow>=1.3.0; extra == 'sqlalchemy'
Requires-Dist: flask-sqlalchemy>=3.1.1; extra == 'sqlalchemy'
Requires-Dist: sqlalchemy-utils>=0.41.2; extra == 'sqlalchemy'
Requires-Dist: wrapt>=1.17.2; extra == 'sqlalchemy'
